dalec_discourse/__init__.py
dalec_discourse/apps.py
dalec_discourse/proxy.py
dalec_discourse-0.1.3.dist-info/AUTHORS
dalec_discourse-0.1.3.dist-info/LICENSE
dalec_discourse-0.1.3.dist-info/METADATA
dalec_discourse-0.1.3.dist-info/WHEEL
dalec_discourse-0.1.3.dist-info/top_level.txt
dalec_discourse-0.1.3.dist-info/RECORD
